{"nodes": [{"id": "bug_audio_empty_src", "label": "Audio playback empty src error (code 4)", "file_type": "concept", "source_file": "apps/electron/BUGFIXES_2026-02-27.md", "source_location": null, "source_url": null, "captured_at": null, "author": null, "contributor": null}, {"id": "bug_panel_size", "label": "ResizablePanel invalid layout total (120%)", "file_type": "concept", "source_file": "apps/electron/BUGFIXES_2026-02-27.md", "source_location": null, "source_url": null, "captured_at": null, "author": null, "contributor": null}, {"id": "bug_transcription_stuck", "label": "Transcription stuck in progress (no API key)", "file_type": "concept", "source_file": "apps/electron/BUGFIXES_2026-02-27.md", "source_location": null, "source_url": null, "captured_at": null, "author": null, "contributor": null}], "edges": [{"source": "bug_audio_empty_src", "target": "use_audio_playback", "relation": "references", "confidence": "EXTRACTED", "confidence_score": 1.0, "source_file": "apps/electron/BUGFIXES_2026-02-27.md", "source_location": null, "weight": 1.0}, {"source": "bug_panel_size", "target": "tripane_layout", "relation": "references", "confidence": "EXTRACTED", "confidence_score": 1.0, "source_file": "apps/electron/BUGFIXES_2026-02-27.md", "source_location": null, "weight": 1.0}, {"source": "bug_transcription_stuck", "target": "transcription_ts", "relation": "references", "confidence": "EXTRACTED", "confidence_score": 1.0, "source_file": "apps/electron/BUGFIXES_2026-02-27.md", "source_location": null, "weight": 1.0}, {"source": "bug_transcription_stuck", "target": "use_operations", "relation": "references", "confidence": "EXTRACTED", "confidence_score": 1.0, "source_file": "apps/electron/BUGFIXES_2026-02-27.md", "source_location": null, "weight": 1.0}], "hyperedges": []}